MultiBgolearn/__init__.py
MultiBgolearn/bgo.py
MultiBgolearn/utility/acquisition.py
MultiBgolearn/utility/funs.py
MultiBgolearn 原版备份/__init__.py
MultiBgolearn 原版备份/bgo.py
multibgolearn-0.1.0.dist-info/METADATA
multibgolearn-0.1.0.dist-info/WHEEL
multibgolearn-0.1.0.dist-info/top_level.txt
multibgolearn-0.1.0.dist-info/RECORD
