Metadata-Version: 2.4
Name: MultiBgolearn
Version: 0.1.0
Summary: Python package designed for multi-objective Bayesian global optimization (MOBO)
Home-page: https://github.com/Bin-Cao/MultiBgolearn
Author: CaoBin
Author-email: bcao686@connect.hkust-gz.edu.cn
Maintainer: CaoBin
Maintainer-email: bcao686@connect.hkust-gz.edu.cn
License: MIT License
Classifier: Development Status :: 3 - Alpha
Classifier: Intended Audience :: Developers
Classifier: Topic :: Software Development :: Build Tools
Classifier: License :: OSI Approved :: MIT License
Classifier: Programming Language :: Python :: 3
Requires-Python: >=3.7
Requires-Dist: scikit-learn
Requires-Dist: openpyxl
Requires-Dist: art
Dynamic: author
Dynamic: author-email
Dynamic: classifier
Dynamic: description
Dynamic: home-page
Dynamic: license
Dynamic: maintainer
Dynamic: maintainer-email
Dynamic: requires-dist
Dynamic: requires-python
Dynamic: summary
